CHANGELOG.txt
LICENCE.txt
MANIFEST.in
README.txt
setup.py
FunnyAlerts/__init__.py
FunnyAlerts.egg-info/PKG-INFO
FunnyAlerts.egg-info/SOURCES.txt
FunnyAlerts.egg-info/dependency_links.txt
FunnyAlerts.egg-info/requires.txt
FunnyAlerts.egg-info/top_level.txt
venv/lib/python3.8/site-packages/AVFoundation/__init__.py
venv/lib/python3.8/site-packages/AVFoundation/_metadata.py
venv/lib/python3.8/site-packages/AVKit/__init__.py
venv/lib/python3.8/site-packages/AVKit/_metadata.py
venv/lib/python3.8/site-packages/Accessibility/__init__.py
venv/lib/python3.8/site-packages/Accessibility/_metadata.py
venv/lib/python3.8/site-packages/Accounts/__init__.py
venv/lib/python3.8/site-packages/Accounts/_metadata.py
venv/lib/python3.8/site-packages/AdServices/__init__.py
venv/lib/python3.8/site-packages/AdServices/_metadata.py
venv/lib/python3.8/site-packages/AdSupport/__init__.py
venv/lib/python3.8/site-packages/AdSupport/_metadata.py
venv/lib/python3.8/site-packages/AddressBook/__init__.py
venv/lib/python3.8/site-packages/AddressBook/_metadata.py
venv/lib/python3.8/site-packages/AppKit/__init__.py
venv/lib/python3.8/site-packages/AppKit/_metadata.py
venv/lib/python3.8/site-packages/AppKit/_nsapp.py
venv/lib/python3.8/site-packages/AppTrackingTransparency/__init__.py
venv/lib/python3.8/site-packages/AppTrackingTransparency/_metadata.py
venv/lib/python3.8/site-packages/AppleScriptKit/__init__.py
venv/lib/python3.8/site-packages/AppleScriptKit/_metadata.py
venv/lib/python3.8/site-packages/AppleScriptObjC/__init__.py
venv/lib/python3.8/site-packages/AppleScriptObjC/_metadata.py
venv/lib/python3.8/site-packages/ApplicationServices/__init__.py
venv/lib/python3.8/site-packages/AudioVideoBridging/__init__.py
venv/lib/python3.8/site-packages/AudioVideoBridging/_metadata.py
venv/lib/python3.8/site-packages/AuthenticationServices/__init__.py
venv/lib/python3.8/site-packages/AuthenticationServices/_metadata.py
venv/lib/python3.8/site-packages/AutomaticAssessmentConfiguration/__init__.py
venv/lib/python3.8/site-packages/AutomaticAssessmentConfiguration/_metadata.py
venv/lib/python3.8/site-packages/Automator/__init__.py
venv/lib/python3.8/site-packages/MouseInfo-0.1.3-py3.8.egg-info/SOURCES.txt
venv/lib/python3.8/site-packages/MouseInfo-0.1.3-py3.8.egg-info/dependency_links.txt
venv/lib/python3.8/site-packages/MouseInfo-0.1.3-py3.8.egg-info/installed-files.txt
venv/lib/python3.8/site-packages/MouseInfo-0.1.3-py3.8.egg-info/requires.txt
venv/lib/python3.8/site-packages/MouseInfo-0.1.3-py3.8.egg-info/top_level.txt
venv/lib/python3.8/site-packages/Pillow-9.1.0.dist-info/top_level.txt
venv/lib/python3.8/site-packages/PyAutoGUI-0.9.53-py3.8.egg-info/SOURCES.txt
venv/lib/python3.8/site-packages/PyAutoGUI-0.9.53-py3.8.egg-info/dependency_links.txt
venv/lib/python3.8/site-packages/PyAutoGUI-0.9.53-py3.8.egg-info/installed-files.txt
venv/lib/python3.8/site-packages/PyAutoGUI-0.9.53-py3.8.egg-info/requires.txt
venv/lib/python3.8/site-packages/PyAutoGUI-0.9.53-py3.8.egg-info/top_level.txt
venv/lib/python3.8/site-packages/PyGetWindow-0.0.9-py3.8.egg-info/SOURCES.txt
venv/lib/python3.8/site-packages/PyGetWindow-0.0.9-py3.8.egg-info/dependency_links.txt
venv/lib/python3.8/site-packages/PyGetWindow-0.0.9-py3.8.egg-info/installed-files.txt
venv/lib/python3.8/site-packages/PyGetWindow-0.0.9-py3.8.egg-info/requires.txt
venv/lib/python3.8/site-packages/PyGetWindow-0.0.9-py3.8.egg-info/top_level.txt
venv/lib/python3.8/site-packages/PyMsgBox-1.0.9.dist-info/top_level.txt
venv/lib/python3.8/site-packages/PyRect-0.2.0-py3.8.egg-info/SOURCES.txt
venv/lib/python3.8/site-packages/PyRect-0.2.0-py3.8.egg-info/dependency_links.txt
venv/lib/python3.8/site-packages/PyRect-0.2.0-py3.8.egg-info/installed-files.txt
venv/lib/python3.8/site-packages/PyRect-0.2.0-py3.8.egg-info/top_level.txt
venv/lib/python3.8/site-packages/PyScreeze-0.1.28.dist-info/AUTHORS.txt
venv/lib/python3.8/site-packages/PyScreeze-0.1.28.dist-info/LICENSE.txt
venv/lib/python3.8/site-packages/PyScreeze-0.1.28.dist-info/top_level.txt
venv/lib/python3.8/site-packages/pip-22.0.4.dist-info/LICENSE.txt
venv/lib/python3.8/site-packages/pip-22.0.4.dist-info/entry_points.txt
venv/lib/python3.8/site-packages/pip-22.0.4.dist-info/top_level.txt
venv/lib/python3.8/site-packages/pyobjc-8.5.dist-info/top_level.txt
venv/lib/python3.8/site-packages/pyobjc_core-8.5.dist-info/namespace_packages.txt
venv/lib/python3.8/site-packages/pyobjc_core-8.5.dist-info/top_level.txt
venv/lib/python3.8/site-packages/pyobjc_framework_AVFoundation-8.5.dist-info/top_level.txt
venv/lib/python3.8/site-packages/pyobjc_framework_AVKit-8.5.dist-info/top_level.txt
venv/lib/python3.8/site-packages/pyobjc_framework_Accessibility-8.5.dist-info/top_level.txt
venv/lib/python3.8/site-packages/pyobjc_framework_Accounts-8.5.dist-info/LICENSE.txt
venv/lib/python3.8/site-packages/pyobjc_framework_Accounts-8.5.dist-info/top_level.txt
venv/lib/python3.8/site-packages/pyobjc_framework_AdServices-8.5.dist-info/top_level.txt
venv/lib/python3.8/site-packages/pyobjc_framework_AdSupport-8.5.dist-info/top_level.txt
venv/lib/python3.8/site-packages/pyobjc_framework_AddressBook-8.5.dist-info/LICENSE.txt
venv/lib/python3.8/site-packages/pyobjc_framework_AddressBook-8.5.dist-info/top_level.txt
venv/lib/python3.8/site-packages/pyobjc_framework_AppTrackingTransparency-8.5.dist-info/top_level.txt
venv/lib/python3.8/site-packages/pyobjc_framework_AppleScriptKit-8.5.dist-info/LICENSE.txt
venv/lib/python3.8/site-packages/pyobjc_framework_AppleScriptKit-8.5.dist-info/top_level.txt
venv/lib/python3.8/site-packages/pyobjc_framework_AppleScriptObjC-8.5.dist-info/LICENSE.txt
venv/lib/python3.8/site-packages/pyobjc_framework_AppleScriptObjC-8.5.dist-info/top_level.txt
venv/lib/python3.8/site-packages/pyobjc_framework_ApplicationServices-8.5.dist-info/top_level.txt
venv/lib/python3.8/site-packages/pyobjc_framework_AudioVideoBridging-8.5.dist-info/top_level.txt
venv/lib/python3.8/site-packages/pyobjc_framework_AuthenticationServices-8.5.dist-info/top_level.txt
