Metadata-Version: 2.1
Name: FunnyAlerts
Version: 0.0.4
Summary: Funny alerts to prank a friends
Home-page: 
Author: Jan Kołodziej
Author-email: jankolodziej04@gmail.com
License: MIT
Keywords: alerts
Platform: UNKNOWN
Classifier: Development Status :: 5 - Production/Stable
Classifier: Intended Audience :: Education
Classifier: Operating System :: Microsoft :: Windows :: Windows 10
Classifier: License :: OSI Approved :: MIT License
Classifier: Programming Language :: Python :: 3
License-File: LICENCE.txt
